{"examples.md":"D7tX-Mef","examples_cartopy_annotation.md":"Bl40y0a7","examples_axis_config.md":"ifdEsVJV","examples_field_and_countries.md":"vEbbhCEB","examples_geostationary_image.md":"DUdRXnfl","examples_german_lakes.md":"Bzc67lRA","examples_gmt_antioquia.md":"DO_T08Le","examples_healpix.md":"CS3DifCm","examples_basic.md":"DKwsa1bk","architecture.md":"CVRTE408","examples_rasters.md":"D0ADAjFE","examples_meshimage.md":"ChOmTjNo","examples_is_it_a_plane.md":"BUKe7Ge1","examples_italy.md":"DUQBo2Qe","examples_contours.md":"BAY-aK6Z","adding_demos.md":"B1YAGsl2","examples_new.md":"cKKLK-Ji","examples_tissot.md":"Daoq3sle","examples_rotating_earth.md":"D6RUBe_N","examples_cartopy_arrows.md":"D5rXOEvH","data.md":"C0m9TQoK","examples_graph_on_usa.md":"BawCxdG4","examples_projections.md":"COlWQGGo","examples_multiple_crs.md":"cGbArRvV","examples_orthographic.md":"NLXYdqNu","nonlinear_transforms.md":"B9YAI3zZ","examples_cartopy_katrina.md":"DjjWG1w9","index.md":"BCtIJh2q","examples_cartopy_streamplot.md":"Bbrp4X-n","introduction.md":"DIzrIOjH","examples_world_population.md":"B6knHDPE","examples_histogram.md":"C4AaLNAZ"}
